lab2/add4.v
module add4(a, b, c, d, sum, ov);

       input [3:0] a, b, c, d;
       output [4:0] sum;
       output ov;


       assign sum = a + b + c + d + sum;
       assign ov = 1'b0;

endmodule

lab2/testbench_add4.v
`timescale 1ns / 1ps
module testbench_add4;

reg [3:0] a, b, c, d;
wire [4:0] sum;
wire ov;
reg clk;
reg rst;
reg [4:0] correct_sum;
reg [20:0] test_num;
reg correct_ov;


always #0.001 clk = ~clk;

always #0.001 rst = ~rst;

add4 ABC(a, b, c, d, sum, ov);

initial
begin
	clk <= 0;
	rst <= 0;
	a <= 0; 
	b <= 0;
	c <= 0;
	d <= 0;
	test_num <= 0;
	$dumpfile("add4.vcd");
	$dumpvars;
end

always@(posedge clk or negedge rst)
begin
	if(rst)begin
		if(a <= 15) begin 
			a <= a + 1;
			test_num <= test_num + 1;
		end 
		if(a == 15) begin
			b <= b + 1;
		end
		if(a == 15 && b == 15) begin;
			c <= c + 1;
		end
		if(a == 15 && b == 15 && c == 15) begin
			d <= d + 1;
		end
		if(a == 15 && b == 15 && c == 15 && d == 15) begin
			$finish;
		end
	end
	else begin
		{correct_ov, correct_sum} = a + b + c+ d;
		if({ov, sum} == {correct_ov, correct_sum}) begin
			$display ("Test %d ", test_num);
			$display ("CORRECT! No overflow.");
			$display ("%d + %d + %d + %d = ?", a, b, c, d);
			$display ("your answer: ov = %d, sum = %d", ov, sum);
			$display ("correct answer: ov = %d, sum = %d", ov, sum);
			$display ("\n");
		end
		else begin
			$display ("Test %d ", test_num);
			$display ("///////////////////////");
			$display ("//////// Fail! ////////");
			$display ("/// Occur Overflow! ///");
			$display ("///////////////////////");
			$display ("%d + %d + %d + %d = ?", a, b, c, d);
			$display ("your answer: ov = %d, sum = %d", ov, sum);
			$display ("correct answer: ov = %d, sum = %d", correct_ov, correct_sum);
			$display ("\n");
		end
	end
end
initial #1005 $finish;
endmodule

lab2/add4.vcd
$date
	Tue Apr 27 22:52:50 2021
$end
$version
	Icarus Verilog
$end
$timescale
	1ps
$end
$scope module testbench_add4 $end
$var wire 1 ! ov $end
$var wire 5 " sum [4:0] $end
$var reg 4 # a [3:0] $end
$var reg 4 $ b [3:0] $end
$var reg 4 % c [3:0] $end
$var reg 1 & clk $end
$var reg 1 ' correct_ov $end
$var reg 5 ( correct_sum [4:0] $end
$var reg 4 ) d [3:0] $end
$var reg 1 * rst $end
$var reg 21 + test_num [20:0] $end
$scope module ABC $end
$var wire 4 , a [3:0] $end
$var wire 4 - b [3:0] $end
$var wire 4 . c [3:0] $end
$var wire 4 / d [3:0] $end
$var wire 1 ! ov $end
$var wire 5 0 sum [4:0] $end
$upscope $end
$upscope $end
$enddefinitions $end
#0
$dumpvars
bx 0
b0 /
b0 .
b0 -
b0 ,
b0 +
0*
b0 )
b0 (
0'
0&
b0 %
b0 $
b0 #
bx "
0!
$end
#1
b1 +
b1 #
b1 ,
1*
1&
#2
b1 (
0*
0&
#3
b10 +
b10 #
b10 ,
1*
1&
#4
b10 (
0*
0&
#5
b11 +
b11 #
b11 ,
1*
1&
#6
b11 (
0*
0&
#7
b100 +
b100 #
b100 ,
1*
1&
#8
b100 (
0*
0&
#9
b101 +
b101 #
b101 ,
1*
1&
#10
b101 (
0*
0&
#11
b110 +
b110 #
b110 ,
1*
1&
#12
b110 (
0*
0&
#13
b111 +
b111 #
b111 ,
1*
1&
#14
b111 (
0*
0&
#15
b1000 +
b1000 #
b1000 ,
1*
1&
#16
b1000 (
0*
0&
#17
b1001 +
b1001 #
b1001 ,
1*
1&
#18
b1001 (
0*
0&
#19
b1010 +
b1010 #
b1010 ,
1*
1&
#20
b1010 (
0*
0&
#21
b1011 +
b1011 #
b1011 ,
1*
1&
#22
b1011 (
0*
0&
#23
b1100 +
b1100 #
b1100 ,
1*
1&
#24
b1100 (
0*
0&
#25
b1101 +
b1101 #
b1101 ,
1*
1&
#26
b1101 (
0*
0&
#27
b1110 +
b1110 #
b1110 ,
1*
1&
#28
b1110 (
0*
0&
#29
b1111 +
b1111 #
b1111 ,
1*
1&
#30
b1111 (
0*
0&
#31
b1 $
b1 -
b10000 +
b0 #
b0 ,
1*
1&
#32
b1 (
0*
0&
#33
b10001 +
b1 #
b1 ,
1*
1&
#34
b10 (
0*
0&
#35
b10010 +
b10 #
b10 ,
1*
1&
#36
b11 (
0*
0&
#37
b10011 +
b11 #
b11 ,
1*
1&
#38
b100 (
0*
0&
#39
b10100 +
b100 #
b100 ,
1*
1&
#40
b101 (
0*
0&
#41
b10101 +
b101 #
b101 ,
1*
1&
#42
b110 (
0*
0&
#43
b10110 +
b110 #
b110 ,
1*
1&
#44
b111 (
0*
0&
#45
b10111 +
b111 #
b111 ,
1*
1&
#46
b1000 (
0*
0&
#47
b11000 +
b1000 #
b1000 ,
1*
1&
#48
b1001 (
0*
0&
#49
b11001 +
b1001 #
b1001 ,
1*
1&
#50
b1010 (
0*
0&
#51
b11010 +
b1010 #
b1010 ,
1*
1&
#52
b1011 (
0*
0&
#53
b11011 +
b1011 #
b1011 ,
1*
1&
#54
b1100 (
0*
0&
#55
b11100 +
b1100 #
b1100 ,
1*
1&
#56
b1101 (
0*
0&
#57
b11101 +
b1101 #
b1101 ,
1*
1&
#58
b1110 (
0*
0&
#59
b11110 +
b1110 #
b1110 ,
1*
1&
#60
b1111 (
0*
0&
#61
b11111 +
b1111 #
b1111 ,
1*
1&
#62
b10000 (
0*
0&
#63
b10 $
b10 -
b100000 +
b0 #
b0 ,
1*
1&
#64
b10 (
0*
0&
#65
b100001 +
b1 #
b1 ,
1*
1&
#66
b11 (
0*
0&
#67
b100010 +
b10 #
b10 ,
1*
1&
#68
b100 (
0*
0&
#69
b100011 +
b11 #
b11 ,
1*
1&
#70
b101 (
0*
0&
#71
b100100 +
b100 #
b100 ,
1*
1&
#72
b110 (
0*
0&
#73
b100101 +
b101 #
b101 ,
1*
1&
#74
b111 (
0*
0&
#75
b100110 +
b110 #
b110 ,
1*
1&
#76
b1000 (
0*
0&
#77
b100111 +
b111 #
b111 ,
1*
1&
#78
b1001 (
0*
0&
#79
b101000 +
b1000 #
b1000 ,
1*
1&
#80
b1010 (
0*
0&
#81
b101001 +
b1001 #
b1001 ,
1*
1&
#82
b1011 (
0*
0&
#83
b101010 +
b1010 #
b1010 ,
1*
1&
#84
b1100 (
0*
0&
#85
b101011 +
b1011 #
b1011 ,
1*
1&
#86
b1101 (
0*
0&
#87
b101100 +
b1100 #
b1100 ,
1*
1&
#88
b1110 (
0*
0&
#89
b101101 +
b1101 #
b1101 ,
1*
1&
#90
b1111 (
0*
0&
#91
b101110 +
b1110 #
b1110 ,
1*
1&
#92
b10000 (
0*
0&
#93
b101111 +
b1111 #
b1111 ,
1*
1&
#94
b10001 (
0*
0&
#95
b11 $
b11 -
b110000 +
b0 #
b0 ,
1*
1&
#96
b11 (
0*
0&
#97
b110001 +
b1 #
b1 ,
1*
1&
#98
b100 (
0*
0&
#99
b110010 +
b10 #
b10 ,
1*
1&
#100
b101 (
0*
0&
#101
b110011 +
b11 #
b11 ,
1*
1&
#102
b110 (
0*
0&
#103
b110100 +
b100 #
b100 ,
1*
1&
#104
b111 (
0*
0&
#105
b110101 +
b101 #
b101 ,
1*
1&
#106
b1000 (
0*
0&
#107
b110110 +
b110 #
b110 ,
1*
1&
#108
b1001 (
0*
0&
#109
b110111 +
b111 #
b111 ,
1*
1&
#110
b1010 (
0*
0&
#111
b111000 +
b1000 #
b1000 ,
1*
1&
#112
b1011 (
0*
0&
#113
b111001 +
b1001 #
b1001 ,
1*
1&
#114
b1100 (
0*
0&
#115
b111010 +
b1010 #
b1010 ,
1*
1&
#116
b1101 (
0*
0&
#117
b111011 +
b1011 #
b1011 ,
1*
1&
#118
b1110 (
0*
0&
#119
b111100 +
b1100 #
b1100 ,
1*
1&
#120
b1111 (
0*
0&
#121
b111101 +
b1101 #
b1101 ,
1*
1&
#122
b10000 (
0*
0&
#123
b111110 +
b1110 #
b1110 ,
1*
1&
#124
b10001 (
0*
0&
#125
b111111 +
b1111 #
b1111 ,
1*
1&
#126
b10010 (
0*
0&
#127
b100 $
b100 -
b1000000 +
b0 #
b0 ,
1*
1&
#128
b100 (
0*
0&
#129
b1000001 +
b1 #
b1 ,
1*
1&
#130
b101 (
0*
0&
#131
b1000010 +
b10 #
b10 ,
1*
1&
#132
b110 (
0*
0&
#133
b1000011 +
b11 #
b11 ,
1*
1&
#134
b111 (
0*
0&
#135
b1000100 +
b100 #
b100 ,
1*
1&
#136
b1000 (
0*
0&
#137
b1000101 +
b101 #
b101 ,
1*
1&
#138
b1001 (
0*
0&
#139
b1000110 +
b110 #
b110 ,
1*
1&
#140
b1010 (
0*
0&
#141
b1000111 +
b111 #
b111 ,
1*
1&
#142
b1011 (
0*
0&
#143
b1001000 +
b1000 #
b1000 ,
1*
1&
#144
b1100 (
0*
0&
#145
b1001001 +
b1001 #
b1001 ,
1*
1&
#146
b1101 (
0*
0&
#147
b1001010 +
b1010 #
b1010 ,
1*
1&
#148
b1110 (
0*
0&
#149
b1001011 +
b1011 #
b1011 ,
1*
1&
#150
b1111 (
0*
0&
#151
b1001100 +
b1100 #
b1100 ,
1*
1&
#152
b10000 (
0*
0&
#153
b1001101 +
b1101 #
b1101 ,
1*
1&
#154
b10001 (
0*
0&
#155
b1001110 +
b1110 #
b1110 ,
1*
1&
#156
b10010 (
0*
0&
#157
b1001111 +
b1111 #
b1111 ,
1*
1&
#158
b10011 (
0*
0&
#159
b101 $
b101 -
b1010000 +
b0 #
b0 ,
1*
1&
#160
b101 (
0*
0&
#161
b1010001 +
b1 #
b1 ,
1*
1&
#162
b110 (
0*
0&
#163
b1010010 +
b10 #
b10 ,
1*
1&
#164
b111 (
0*
0&
#165
b1010011 +
b11 #
b11 ,
1*
1&
#166
b1000 (
0*
0&
#167
b1010100 +
b100 #
b100 ,
1*
1&
#168
b1001 (
0*
0&
#169
b1010101 +
b101 #
b101 ,
1*
1&
#170
b1010 (
0*
0&
#171
b1010110 +
b110 #
b110 ,
1*
1&
#172
b1011 (
0*
0&
#173
b1010111 +
b111 #
b111 ,
1*
1&
#174
b1100 (
0*
0&
#175
b1011000 +
b1000 #
b1000 ,
1*
1&
#176
b1101 (
0*
0&
#177
b1011001 +
b1001 #
b1001 ,
1*
1&
#178
b1110 (
0*
0&
#179
b1011010 +
b1010 #
b1010 ,
1*
1&
#180
b1111 (
0*
0&
#181
b1011011 +
b1011 #
b1011 ,
1*
1&
#182
b10000 (
0*
0&
#183
b1011100 +
b1100 #
b1100 ,
1*
1&
#184
b10001 (
0*
0&
#185
b1011101 +
b1101 #
b1101 ,
1*
1&
#186
b10010 (
0*
0&
#187
b1011110 +
b1110 #
b1110 ,
1*
1&
#188
b10011 (
0*
0&
#189
b1011111 +
b1111 #
b1111 ,
1*
1&
#190
b10100 (
0*
0&
#191
b110 $
b110 -
b1100000 +
b0 #
b0 ,
1*
1&
#192
b110 (
0*
0&
#193
b1100001 +
b1 #
b1 ,
1*
1&
#194
b111 (
0*
0&
#195
b1100010 +
b10 #
b10 ,
1*
1&
#196
b1000 (
0*
0&
#197
b1100011 +
b11 #
b11 ,
1*
1&
#198
b1001 (
0*
0&
#199
b1100100 +
b100 #
b100 ,
1*
1&
#200
b1010 (
0*
0&
#201
b1100101 +
b101 #
b101 ,
1*
1&
#202
b1011 (
0*
0&
#203
b1100110 +
b110 #
b110 ,
1*
1&
#204
b1100 (
0*
0&
#205
b1100111 +
b111 #
b111 ,
1*
1&
#206
b1101 (
0*
0&
#207
b1101000 +
b1000 #
b1000 ,
1*
1&
#208
b1110 (
0*
0&
#209
b1101001 +
b1001 #
b1001 ,
1*
1&
#210
b1111 (
0*
0&
#211
b1101010 +
b1010 #
b1010 ,
1*
1&
#212
b10000 (
0*
0&
#213
b1101011 +
b1011 #
b1011 ,
1*
1&
#214
b10001 (
0*
0&
#215
b1101100 +
b1100 #
b1100 ,
1*
1&
#216
b10010 (
0*
0&
#217
b1101101 +
b1101 #
b1101 ,
1*
1&
#218
b10011 (
0*
0&
#219
b1101110 +
b1110 #
b1110 ,
1*
1&
#220
b10100 (
0*
0&
#221
b1101111 +
b1111 #
b1111 ,
1*
1&
#222
b10101 (
0*
0&
#223
b111 $
b111 -
b1110000 +
b0 #
b0 ,
1*
1&
#224
b111 (
0*
0&
#225
b1110001 +
b1 #
b1 ,
1*
1&
#226
b1000 (
0*
0&
#227
b1110010 +
b10 #
b10 ,
1*
1&
#228
b1001 (
0*
0&
#229
b1110011 +
b11 #
b11 ,
1*
1&
#230
b1010 (
0*
0&
#231
b1110100 +
b100 #
b100 ,
1*
1&
#232
b1011 (
0*
0&
#233
b1110101 +
b101 #
b101 ,
1*
1&
#234
b1100 (
0*
0&
#235
b1110110 +
b110 #
b110 ,
1*
1&
#236
b1101 (
0*
0&
#237
b1110111 +
b111 #
b111 ,
1*
1&
#238
b1110 (
0*
0&
#239
b1111000 +
b1000 #
b1000 ,
1*
1&
#240
b1111 (
0*
0&
#241
b1111001 +
b1001 #
b1001 ,
1*
1&
#242
b10000 (
0*
0&
#243
b1111010 +
b1010 #
b1010 ,
1*
1&
#244
b10001 (
0*
0&
#245
b1111011 +
b1011 #
b1011 ,
1*
1&
#246
b10010 (
0*
0&
#247
b1111100 +
b1100 #
b1100 ,
1*
1&
#248
b10011 (
0*
0&
#249
b1111101 +
b1101 #
b1101 ,
1*
1&
#250
b10100 (
0*
0&
#251
b1111110 +
b1110 #
b1110 ,
1*
1&
#252
b10101 (
0*
0&
#253
b1111111 +
b1111 #
b1111 ,
1*
1&
#254
b10110 (
0*
0&
#255
b1000 $
b1000 -
b10000000 +
b0 #
b0 ,
1*
1&
#256
b1000 (
0*
0&
#257
b10000001 +
b1 #
b1 ,
1*
1&
#258
b1001 (
0*
0&
#259
b10000010 +
b10 #
b10 ,
1*
1&
#260
b1010 (
0*
0&
#261
b10000011 +
b11 #
b11 ,
1*
1&
#262
b1011 (
0*
0&
#263
b10000100 +
b100 #
b100 ,
1*
1&
#264
b1100 (
0*
0&
#265
b10000101 +
b101 #
b101 ,
1*
1&
#266
b1101 (
0*
0&
#267
b10000110 +
b110 #
b110 ,
1*
1&
#268
b1110 (
0*
0&
#269
b10000111 +
b111 #
b111 ,
1*
1&
#270
b1111 (
0*
0&
#271
b10001000 +
b1000 #
b1000 ,
1*
1&
#272
b10000 (
0*
0&
#273
b10001001 +
b1001 #
b1001 ,
1*
1&
#274
b10001 (
0*
0&
#275
b10001010 +
b1010 #
b1010 ,
1*
1&
#276
b10010 (
0*
0&
#277
b10001011 +
b1011 #
b1011 ,
1*
1&
#278
b10011 (
0*
0&
#279
b10001100 +
b1100 #
b1100 ,
1*
1&
#280
b10100 (
0*
0&
#281
b10001101 +
b1101 #
b1101 ,
1*
1&
#282
b10101 (
0*
0&
#283
b10001110 +
b1110 #
b1110 ,
1*
1&
#284
b10110 (
0*
0&
#285
b10001111 +
b1111 #
b1111 ,
1*
1&
#286
b10111 (
0*
0&
#287
b1001 $
b1001 -
b10010000 +
b0 #
b0 ,
1*
1&
#288
b1001 (
0*
0&
#289
b10010001 +
b1 #
b1 ,
1*
1&
#290
b1010 (
0*
0&
#291
b10010010 +
b10 #
b10 ,
1*
1&
#292
b1011 (
0*
0&
#293
b10010011 +
b11 #
b11 ,
1*
1&
#294
b1100 (
0*
0&
#295
b10010100 +
b100 #
b100 ,
1*
1&
#296
b1101 (
0*
0&
#297
b10010101 +
b101 #
b101 ,
1*
1&
#298
b1110 (
0*
0&
#299
b10010110 +
b110 #
b110 ,
1*
1&
#300
b1111 (
0*
0&
#301
b10010111 +
b111 #
b111 ,
1*
1&
#302
b10000 (
0*
0&
#303
b10011000 +
b1000 #
b1000 ,
1*
1&
#304
b10001 (
0*
0&
#305
b10011001 +
b1001 #
b1001 ,
1*
1&
#306
b10010 (
0*
0&
#307
b10011010 +
b1010 #
b1010 ,
1*
1&
#308
b10011 (
0*
0&
#309
b10011011 +
b1011 #
b1011 ,
1*
1&
#310
b10100 (
0*
0&
#311
b10011100 +
b1100 #
b1100 ,
1*
1&
#312
b10101 (
0*
0&
#313
b10011101 +
b1101 #
b1101 ,
1*
1&
#314
b10110 (
0*
0&
#315
b10011110 +
b1110 #
b1110 ,
1*
1&
#316
b10111 (
0*
0&
#317
b10011111 +
b1111 #
b1111 ,
1*
1&
#318
b11000 (
0*
0&
#319
b1010 $
b1010 -
b10100000 +
b0 #
b0 ,
1*
1&
#320
b1010 (
0*
0&
#321
b10100001 +
b1 #
b1 ,
1*
1&
#322
b1011 (
0*
0&
#323
b10100010 +
b10 #
b10 ,
1*
1&
#324
b1100 (
0*
0&
#325
b10100011 +
b11 #
b11 ,
1*
1&
#326
b1101 (
0*
0&
#327
b10100100 +
b100 #
b100 ,
1*
1&
#328
b1110 (
0*
0&
#329
b10100101 +
b101 #
b101 ,
1*
1&
#330
b1111 (
0*
0&
#331
b10100110 +
b110 #
b110 ,
1*
1&
#332
b10000 (
0*
0&
#333
b10100111 +
b111 #
b111 ,
1*
1&
#334
b10001 (
0*
0&
#335
b10101000 +
b1000 #
b1000 ,
1*
1&
#336
b10010 (
0*
0&
#337
b10101001 +
b1001 #
b1001 ,
1*
1&
#338
b10011 (
0*
0&
#339
b10101010 +
b1010 #
b1010 ,
1*
1&
#340
b10100 (
0*
0&
#341
b10101011 +
b1011 #
b1011 ,
1*
1&
#342
b10101 (
0*
0&
#343
b10101100 +
b1100 #
b1100 ,
1*
1&
#344
b10110 (
0*
0&
#345
b10101101 +
b1101 #
b1101 ,
1*
1&
#346
b10111 (
0*
0&
#347
b10101110 +
b1110 #
b1110 ,
1*
1&
#348
b11000 (
0*
0&
#349
b10101111 +
b1111 #
b1111 ,
1*
1&
#350
b11001 (
0*
0&
#351
b1011 $
b1011 -
b10110000 +
b0 #
b0 ,
1*
1&
#352
b1011 (
0*
0&
#353
b10110001 +
b1 #
b1 ,
1*
1&
#354
b1100 (
0*
0&
#355
b10110010 +
b10 #
b10 ,
1*
1&
#356
b1101 (
0*
0&
#357
b10110011 +
b11 #
b11 ,
1*
1&
#358
b1110 (
0*
0&
#359
b10110100 +
b100 #
b100 ,
1*
1&
#360
b1111 (
0*
0&
#361
b10110101 +
b101 #
b101 ,
1*
1&
#362
b10000 (
0*
0&
#363
b10110110 +
b110 #
b110 ,
1*
1&
#364
b10001 (
0*
0&
#365
b10110111 +
b111 #
b111 ,
1*
1&
#366
b10010 (
0*
0&
#367
b10111000 +
b1000 #
b1000 ,
1*
1&
#368
b10011 (
0*
0&
#369
b10111001 +
b1001 #
b1001 ,
1*
1&
#370
b10100 (
0*
0&
#371
b10111010 +
b1010 #
b1010 ,
1*
1&
#372
b10101 (
0*
0&
#373
b10111011 +
b1011 #
b1011 ,
1*
1&
#374
b10110 (
0*
0&
#375
b10111100 +
b1100 #
b1100 ,
1*
1&
#376
b10111 (
0*
0&
#377
b10111101 +
b1101 #
b1101 ,
1*
1&
#378
b11000 (
0*
0&
#379
b10111110 +
b1110 #
b1110 ,
1*
1&
#380
b11001 (
0*
0&
#381
b10111111 +
b1111 #
b1111 ,
1*
1&
#382
b11010 (
0*
0&
#383
b1100 $
b1100 -
b11000000 +
b0 #
b0 ,
1*
1&
#384
b1100 (
0*
0&
#385
b11000001 +
b1 #
b1 ,
1*
1&
#386
b1101 (
0*
0&
#387
b11000010 +
b10 #
b10 ,
1*
1&
#388
b1110 (
0*
0&
#389
b11000011 +
b11 #
b11 ,
1*
1&
#390
b1111 (
0*
0&
#391
b11000100 +
b100 #
b100 ,
1*
1&
#392
b10000 (
0*
0&
#393
b11000101 +
b101 #
b101 ,
1*
1&
#394
b10001 (
0*
0&
#395
b11000110 +
b110 #
b110 ,
1*
1&
#396
b10010 (
0*
0&
#397
b11000111 +
b111 #
b111 ,
1*
1&
#398
b10011 (
0*
0&
#399
b11001000 +
b1000 #
b1000 ,
1*
1&
#400
b10100 (
0*
0&
#401
b11001001 +
b1001 #
b1001 ,
1*
1&
#402
b10101 (
0*
0&
#403
b11001010 +
b1010 #
b1010 ,
1*
1&
#404
b10110 (
0*
0&
#405
b11001011 +
b1011 #
b1011 ,
1*
1&
#406
b10111 (
0*
0&
#407
b11001100 +
b1100 #
b1100 ,
1*
1&
#408
b11000 (
0*
0&
#409
b11001101 +
b1101 #
b1101 ,
1*
1&
#410
b11001 (
0*
0&
#411
b11001110 +
b1110 #
b1110 ,
1*
1&
#412
b11010 (
0*
0&
#413
b11001111 +
b1111 #
b1111 ,
1*
1&
#414
b11011 (
0*
0&
#415
b1101 $
b1101 -
b11010000 +
b0 #
b0 ,
1*
1&
#416
b1101 (
0*
0&
#417
b11010001 +
b1 #
b1 ,
1*
1&
#418
b1110 (
0*
0&
#419
b11010010 +
b10 #
b10 ,
1*
1&
#420
b1111 (
0*
0&
#421
b11010011 +
b11 #
b11 ,
1*
1&
#422
b10000 (
0*
0&
#423
b11010100 +
b100 #
b100 ,
1*
1&
#424
b10001 (
0*
0&
#425
b11010101 +
b101 #
b101 ,
1*
1&
#426
b10010 (
0*
0&
#427
b11010110 +
b110 #
b110 ,
1*
1&
#428
b10011 (
0*
0&
#429
b11010111 +
b111 #
b111 ,
1*
1&
#430
b10100 (
0*
0&
#431
b11011000 +
b1000 #
b1000 ,
1*
1&
#432
b10101 (
0*
0&
#433
b11011001 +
b1001 #
b1001 ,
1*
1&
#434
b10110 (
0*
0&
#435
b11011010 +
b1010 #
b1010 ,
1*
1&
#436
b10111 (
0*
0&
#437
b11011011 +
b1011 #
b1011 ,
1*
1&
#438
b11000 (
0*
0&
#439
b11011100 +
b1100 #
b1100 ,
1*
1&
#440
b11001 (
0*
0&
#441
b11011101 +
b1101 #
b1101 ,
1*
1&
#442
b11010 (
0*
0&
#443
b11011110 +
b1110 #
b1110 ,
1*
1&
#444
b11011 (
0*
0&
#445
b11011111 +
b1111 #
b1111 ,
1*
1&
#446
b11100 (
0*
0&
#447
b1110 $
b1110 -
b11100000 +
b0 #
b0 ,
1*
1&
#448
b1110 (
0*
0&
#449
b11100001 +
b1 #
b1 ,
1*
1&
#450
b1111 (
0*
0&
#451
b11100010 +
b10 #
b10 ,
1*
1&
#452
b10000 (
0*
0&
#453
b11100011 +
b11 #
b11 ,
1*
1&
#454
b10001 (
0*
0&
#455
b11100100 +
b100 #
b100 ,
1*
1&
#456
b10010 (
0*
0&
#457
b11100101 +
b101 #
b101 ,
1*
1&
#458
b10011 (
0*
0&
#459
b11100110 +
b110 #
b110 ,
1*
1&
#460
b10100 (
0*
0&
#461
b11100111 +
b111 #
b111 ,
1*
1&
#462
b10101 (
0*
0&
#463
b11101000 +
b1000 #
b1000 ,
1*
1&
#464
b10110 (
0*
0&
#465
b11101001 +
b1001 #
b1001 ,
1*
1&
#466
b10111 (
0*
0&
#467
b11101010 +
b1010 #
b1010 ,
1*
1&
#468
b11000 (
0*
0&
#469
b11101011 +
b1011 #
b1011 ,
1*
1&
#470
b11001 (
0*
0&
#471
b11101100 +
b1100 #
b1100 ,
1*
1&
#472
b11010 (
0*
0&
#473
b11101101 +
b1101 #
b1101 ,
1*
1&
#474
b11011 (
0*
0&
#475
b11101110 +
b1110 #
b1110 ,
1*
1&
#476
b11100 (
0*
0&
#477
b11101111 +
b1111 #
b1111 ,
1*
1&
#478
b11101 (
0*
0&
#479
b1111 $
b1111 -
b11110000 +
b0 #
b0 ,
1*
1&
#480
b1111 (
0*
0&
#481
b11110001 +
b1 #
b1 ,
1*
1&
#482
b10000 (
0*
0&
#483
b11110010 +
b10 #
b10 ,
1*
1&
#484
b10001 (
0*
0&
#485
b11110011 +
b11 #
b11 ,
1*
1&
#486
b10010 (
0*
0&
#487
b11110100 +
b100 #
b100 ,
1*
1&
#488
b10011 (
0*
0&
#489
b11110101 +
b101 #
b101 ,
1*
1&
#490
b10100 (
0*
0&
#491
b11110110 +
b110 #
b110 ,
1*
1&
#492
b10101 (
0*
0&
#493
b11110111 +
b111 #
b111 ,
1*
1&
#494
b10110 (
0*
0&
#495
b11111000 +
b1000 #
b1000 ,
1*
1&
#496
b10111 (
0*
0&
#497
b11111001 +
b1001 #
b1001 ,
1*
1&
#498
b11000 (
0*
0&
#499
b11111010 +
b1010 #
b1010 ,
1*
1&
#500
b11001 (
0*
0&
#501
b11111011 +
b1011 #
b1011 ,
1*
1&
#502
b11010 (
0*
0&
#503
b11111100 +
b1100 #
b1100 ,
1*
1&
#504
b11011 (
0*
0&
#505
b11111101 +
b1101 #
b1101 ,
1*
1&
#506
b11100 (
0*
0&
#507
b11111110 +
b1110 #
b1110 ,
1*
1&
#508
b11101 (
0*
0&
#509
b11111111 +
b1111 #
b1111 ,
1*
1&
#510
b11110 (
0*
0&
#511
b1 %
b1 .
b0 $
b0 -
b100000000 +
b0 #
b0 ,
1*
1&
#512
b1 (
0*
0&
#513
b100000001 +
b1 #
b1 ,
1*
1&
#514
b10 (
0*
0&
#515
b100000010 +
b10 #
b10 ,
1*
1&
#516
b11 (
0*
0&
#517
b100000011 +
b11 #
b11 ,
1*
1&
#518
b100 (
0*
0&
#519
b100000100 +
b100 #
b100 ,
1*
1&
#520
b101 (
0*
0&
#521
b100000101 +
b101 #
b101 ,
1*
1&
#522
b110 (
0*
0&
#523
b100000110 +
b110 #
b110 ,
1*
1&
#524
b111 (
0*
0&
#525
b100000111 +
b111 #
b111 ,
1*
1&
#526
b1000 (
0*
0&
#527
b100001000 +
b1000 #
b1000 ,
1*
1&
#528
b1001 (
0*
0&
#529
b100001001 +
b1001 #
b1001 ,
1*
1&
#530
b1010 (
0*
0&
#531
b100001010 +
b1010 #
b1010 ,
1*
1&
#532
b1011 (
0*
0&
#533
b100001011 +
b1011 #
b1011 ,
1*
1&
#534
b1100 (
0*
0&
#535
b100001100 +
b1100 #
b1100 ,
1*
1&
#536
b1101 (
0*
0&
#537
b100001101 +
b1101 #
b1101 ,
1*
1&
#538
b1110 (
0*
0&
#539
b100001110 +
b1110 #
b1110 ,
1*
1&
#540
b1111 (
0*
0&
#541
b100001111 +
b1111 #
b1111 ,
1*
1&
#542
b10000 (
0*
0&
#543
b1 $
b1 -
b100010000 +
b0 #
b0 ,
1*
1&
#544
b10 (
0*
0&
#545
b100010001 +
b1 #
b1 ,
1*
1&
#546
b11 (
0*
0&
#547
b100010010 +
b10 #
b10 ,
1*
1&
#548
b100 (
0*
0&
#549
b100010011 +
b11 #
b11 ,
1*
1&
#550
b101 (
0*
0&
#551
b100010100 +
b100 #
b100 ,
1*
1&
#552
b110 (
0*
0&
#553
b100010101 +
b101 #
b101 ,
1*
1&
#554
b111 (
0*
0&
#555
b100010110 +
b110 #
b110 ,
1*
1&
#556
b1000 (
0*
0&
#557
b100010111 +
b111 #
b111 ,
1*
1&
#558
b1001 (
0*
0&
#559
b100011000 +
b1000 #
b1000 ,
1*
1&
#560
b1010 (
0*
0&
#561
b100011001 +
b1001 #
b1001 ,
1*
1&
#562
b1011 (
0*
0&
#563
b100011010 +
b1010 #
b1010 ,
1*
1&
#564
b1100 (
0*
0&
#565
b100011011 +
b1011 #
b1011 ,
1*
1&
#566
b1101 (
0*
0&
#567
b100011100 +
b1100 #
b1100 ,
1*
1&
#568
b1110 (
0*
0&
#569
b100011101 +
b1101 #
b1101 ,
1*
1&
#570
b1111 (
0*
0&
#571
b100011110 +
b1110 #
b1110 ,
1*
1&
#572
b10000 (
0*
0&
#573
b100011111 +
b1111 #
b1111 ,
1*
1&
#574
b10001 (
0*
0&
#575
b10 $
b10 -
b100100000 +
b0 #
b0 ,
1*
1&
#576
b11 (
0*
0&
#577
b100100001 +
b1 #
b1 ,
1*
1&
#578
b100 (
0*
0&
#579
b100100010 +
b10 #
b10 ,
1*
1&
#580
b101 (
0*
0&
#581
b100100011 +
b11 #
b11 ,
1*
1&
#582
b110 (
0*
0&
#583
b100100100 +
b100 #
b100 ,
1*
1&
#584
b111 (
0*
0&
#585
b100100101 +
b101 #
b101 ,
1*
1&
#586
b1000 (
0*
0&
#587
b100100110 +
b110 #
b110 ,
1*
1&
#588
b1001 (
0*
0&
#589
b100100111 +
b111 #
b111 ,
1*
1&
#590
b1010 (
0*
0&
#591
b100101000 +
b1000 #
b1000 ,
1*
1&
#592
b1011 (
0*
0&
#593
b100101001 +
b1001 #
b1001 ,
1*
1&
#594
b1100 (
0*
0&
#595
b100101010 +
b1010 #
b1010 ,
1*
1&
#596
b1101 (
0*
0&
#597
b100101011 +
b1011 #
b1011 ,
1*
1&
#598
b1110 (
0*
0&
#599
b100101100 +
b1100 #
b1100 ,
1*
1&
#600
b1111 (
0*
0&
#601
b100101101 +
b1101 #
b1101 ,
1*
1&
#602
b10000 (
0*
0&
#603
b100101110 +
b1110 #
b1110 ,
1*
1&
#604
b10001 (
0*
0&
#605
b100101111 +
b1111 #
b1111 ,
1*
1&
#606
b10010 (
0*
0&
#607
b11 $
b11 -
b100110000 +
b0 #
b0 ,
1*
1&
#608
b100 (
0*
0&
#609
b100110001 +
b1 #
b1 ,
1*
1&
#610
b101 (
0*
0&
#611
b100110010 +
b10 #
b10 ,
1*
1&
#612
b110 (
0*
0&
#613
b100110011 +
b11 #
b11 ,
1*
1&
#614
b111 (
0*
0&
#615
b100110100 +
b100 #
b100 ,
1*
1&
#616
b1000 (
0*
0&
#617
b100110101 +
b101 #
b101 ,
1*
1&
#618
b1001 (
0*
0&
#619
b100110110 +
b110 #
b110 ,
1*
1&
#620
b1010 (
0*
0&
#621
b100110111 +
b111 #
b111 ,
1*
1&
#622
b1011 (
0*
0&
#623
b100111000 +
b1000 #
b1000 ,
1*
1&
#624
b1100 (
0*
0&
#625
b100111001 +
b1001 #
b1001 ,
1*
1&
#626
b1101 (
0*
0&
